{
    "2668P": "DanvilleCityPP",
    "426P": "HenricoCountyPP",
    "1248P": "AnneArundelCountyPP",
    "1247P": "BaltimoreCityPP",
    "1241P": "BaltimoreCountyPP",
    "227P": "MontgomeryCountyPP",
    "1243P": "PrinceGeorgesCountyPP",
    "3532P": "StateofMarylandPP",
    "873P": "DistrictofColumbiaPP",
    "224P": "FraminghamTownPP",
    "847P": "WorcesterCityPP",
    "1397P": "ClarkCountyPP",
    "836P": "AlamedaCountyPP",
    "838P": "ContraCostaCountyPP",
    "1169P": "FresnoCountyPP",
    "835P": "LosAngelesCountyPP",
    "27P": "OrangeCountyPP",
    "867P": "RiversideCountyPP",
    "834P": "SacramentoCountyPP",
    "29P": "SanBernardinoCountyPP",
    "861P": "SanDiegoCountyPP",
    "1165P": "SanJoaquinCountyPP",
    "30P": "SantaClaraCountyPP",
    "1372P": "StanislausCountyPP",
    "1401P": "DetroitCityPP",
    "1401R": "DetroitCityRE",
    "1033P": "MemphisCityPP",
    "1033R": "MemphisCityRE",
    "272P": "CatawbaCountyPP",
    "275P": "GuilfordCountyPP",
    "276P": "IredellCountyPP",
    "277P": "MecklenburgCountyPP",
    "277R": "MecklenburgCountyRE",
    "278P": "NewHanoverCountyPP",
    "281P": "WakeCountyPP",
    "281R": "WakeCountyRE",
    "1399P": "WashoeCountyPP",
    "474P": "FultonCountyPP",
    "849P": "KnoxvilleCityPP",
    "568P": "WilliamsonCountyPP",
    "568R": "WilliamsonCountyRE",
    "3351P": "GalvestonCountyPP",
    "3351R": "GalvestonCountyRE",
    "3669P": "HidalgoCountyPP",
    "3669R": "HidalgoCountyRE",
    "2852P": "LaredoCityPP",
    "2852R": "LaredoCityRE",
    "400P": "NuecesCountyPP",
    "400R": "NuecesCountyRE",
    "1871P": "PotterCountyPP",
    "1871R": "PotterCountyRE",
    "473P": "RichmondCountyPP",
    "473R": "RichmondCountyRE",
    "2436P": "ChathamCountyPP",
    "313P": "MultnomahCountyPP",
    "313R": "MultnomahCountyRE",
    "608P": "BullochCountyPP",
    "712P": "StatesboroCityPP",
    "712R": "StatesboroCityRE",
    "131P": "WyandotteCountyPP",
    "163P": "CaddoParishPP",
    "195P": "EastBatonRougeParishPP",
    "195R": "EastBatonRougeParishPP",
    "201P": "JeffersonParishPP",
    "201R": "JeffersonParishRE",
    "208P": "OuachitaParishPP",
    "208R": "OuachitaParishRE",
    "215P": "StTammanyParishPP",
    "215R": "StTammanyParishRE",
    "4470P": "MaineBETRPP",
    "256P": "StCharlesCountyPP",
    "256R": "StCharlesCountyRE",
    "2373R": "CuyahogaCountyRE",
    "271P": "BuncombeCountyPP",
    "271R": "BuncombeCountyRE",
    "1203P": "DetroitCityWinterPP",
    "1203R": "DetroitCityWinterRE",
    "629P": "CharlestonCountyPP",
    "629R": "CharlestonCountyRE",
    "1121P": "LexingtonCountyPP",
    "1121R": "LexingtonCountyRE",
    "486P": "RichlandCountyPP",
    "486R": "RichlandCountyRE",
    "2349P": "FranklinCountyPP",
    "2349R": "FranklinCountyRE",
    "362P": "CollinCountyPP",
    "362R": "CollinCountyRE",
    "370P": "DentonCountyPP",
    "370R": "DentonCountyRE",
    "371P": "ElPasoCountyPP",
    "371R": "ElPasoCountyRE",
    "374P": "FortBendCountyPP",
    "374R": "FortBendCountyRE",
    "2093P": "GreggCountyPP",
    "2093R": "GreggCountyRE",
    "391P": "LamarCountyTXPP",
    "391R": "LamarCountyTXRE",
    "2500P": "LubbockCountyPP",
    "2500R": "LubbockCountyRE",
    "399P": "MontgomeryCountyPP",
    "399R": "MontgomeryCountyRE",
    "410P": "TravisCountyPP",
    "410R": "TravisCountyRE",
    "1895P": "VictoriaCountyPP",
    "1895R": "VictoriaCountyRE",
    "2851P": "WebbCountyPP",
    "2851R": "WebbCountyRE",
    "800P": "WilliamsonCountyTXPP",
    "800R": "WilliamsonCountyTXRE",
    "1297R": "LamarCountyMSRE",
    "1032P": "ShelbyCountyPP",
    "330P": "SullivanCountyPP",
    "331P": "SumnerCountyPP",
    "331R": "SumnerCountyRE",
    "16P": "SalineCountyPP",
    "16R": "SalineCountyRE",
    "856P": "CookCountyPP",
    "856R": "CookCountyRE",
    "4399P": "LuzerneCountyPP",
    "4399R": "LuzerneCountyRE",
    "36P": "DouglasCountyPP",
    "36R": "DouglasCountyRE",
    "39P": "JeffersonCountyPP",
    "39R": "JeffersonCountyRE",
    "2456R": "KingCountyRE",
    "431P": "KingCountyPP",
    "1723P": "PierceCountyPP",
    "768P": "SpokaneCountyPP",
    "3526R": "SpokaneCountyRE",
    "5793P": "CambriaCountyPP",
    "2013P": "AllenCountyPP",
    "2013R": "AllenCountyRE",
    "101P": "ClarkCountyINPP",
    "101R": "ClarkCountyINRE",
    "2922P": "LakeCountyPP",
    "2922R": "LakeCountyRE",
    "1708P": "LaPorteCountyPP",
    "1708R": "LaPorteCountyRE",
    "114P": "MarionCountyPP",
    "114R": "MarionCountyRE",
    "2306P": "JohnstownCityPP",
    "1102P": "LauderdaleCountyPP",
    "1102R": "LauderdaleCountyRE",
    "15R": "PulaskiCountyRE",
    "15P": "PulaskiCountyPP",
    "5795P": "GreaterJohnstownSchoolDistrictPP",
    "4401R": "WilkesBarreAreaSchoolDistrictRE",
    "378P": "HarrisCountyPP",
    "378R": "HarrisCountyRE",
    "406P": "SmithCountyPP",
    "406R": "SmithCountyRE"
}
